mdpages/__init__.py
mdpages/apps.py
mdpages/tests.py
mdpages/views.py
django_mdpages-0.2.dist-info/LICENSE
django_mdpages-0.2.dist-info/METADATA
django_mdpages-0.2.dist-info/WHEEL
django_mdpages-0.2.dist-info/top_level.txt
django_mdpages-0.2.dist-info/RECORD
