Metadata-Version: 2.1
Name: django-mdpages
Version: 0.2
Summary: A simple Django app to generate pages from files.
Home-page: https://github.com/marcanuy/django-mdpages/
Author: Marcelo Canina
Author-email: me@marcanuy.com
License: MIT License
Project-URL: Source, https://github.com/marcanuy/django-mdpages/
Project-URL: Tracker, https://github.com/marcanuy/django-mdpages/issues
Keywords: django static
Platform: UNKNOWN
Classifier: Environment :: Web Environment
Classifier: Framework :: Django
Classifier: Framework :: Django :: 2.1
Classifier: Intended Audience :: Developers
Classifier: License :: OSI Approved :: MIT License
Classifier: Operating System :: OS Independent
Classifier: Programming Language :: Python
Classifier: Programming Language :: Python :: 3.5
Classifier: Programming Language :: Python :: 3.6
Classifier: Topic :: Internet :: WWW/HTTP
Classifier: Topic :: Internet :: WWW/HTTP :: Dynamic Content
Requires-Dist: Django (>=2.1)
Requires-Dist: Markdown
